vutils/cli/__init__.py
vutils/cli/__init__.pyi
vutils/cli/application.py
vutils/cli/errors.py
vutils/cli/io.py
vutils/cli/logging.py
vutils/cli/py.typed
vutils/cli/version.py
vutils_cli-0.1.2.dist-info/LICENSE
vutils_cli-0.1.2.dist-info/METADATA
vutils_cli-0.1.2.dist-info/WHEEL
vutils_cli-0.1.2.dist-info/top_level.txt
vutils_cli-0.1.2.dist-info/RECORD
