Metadata-Version: 2.1
Name: vutils-cli
Version: 0.1.2
Summary: Auxiliary library for writing CLI applications
Home-page: https://github.com/i386x/vutils-cli
Author: =?utf-8?b?SmnFmcOtIEt1xI1lcmE=?=
Author-email: sanczes@gmail.com
License: MIT
Project-URL: Bug Reports, https://github.com/i386x/vutils-cli/issues
Project-URL: Source, https://github.com/i386x/vutils-cli
Keywords: cli,command-line interface
Platform: any
Classifier: Development Status :: 1 - Planning
Classifier: Environment :: Console
Classifier: Intended Audience :: Developers
Classifier: Intended Audience :: Information Technology
Classifier: License :: OSI Approved :: MIT License
Classifier: Operating System :: OS Independent
Classifier: Programming Language :: Python
Classifier: Programming Language :: Python :: 3
Classifier: Programming Language :: Python :: 3 :: Only
Classifier: Topic :: Software Development
Classifier: Topic :: Software Development :: Libraries
Classifier: Topic :: Software Development :: Libraries :: Python Modules
Classifier: Topic :: Software Development :: User Interfaces
Requires-Python: <4,>=3.7
License-File: LICENSE
Requires-Dist: colorama
Provides-Extra: dev
Requires-Dist: check-manifest ; extra == 'dev'
Provides-Extra: test
Requires-Dist: coverage ; extra == 'test'
